eveprices/__init__.py
eveprices/admin.py
eveprices/apps.py
eveprices/hooks.py
eveprices/models.py
eveprices/tasks.py
eveprices/utils.py
eveprices/management/commands/eveprices_update_prices.py
eveprices/migrations/0001_initial.py
eveprices/migrations/0002_evetycoonconfiguration_and_more.py
eveprices/migrations/0003_remove_evetycoonconfiguration_a_and_more.py
eveprices/migrations/0004_typeprice_and_more.py
eveprices/migrations/0005_janiceconfiguration_api_key.py
eveprices/migrations/__init__.py
eveprices/providers/__init__.py
eveprices/providers/base.py
eveprices/providers/evetycoon.py
eveprices/providers/fuzzwork.py
eveprices/providers/janice.py
eveprices/providers/requests.py
eveprices/templatetags/__init__.py
eveprices/templatetags/eveprices.py
eveprices/tests/__init__.py
eveprices/tests/test_hooks.py
eveprices/tests/test_models.py
eveprices/tests/test_tasks.py
eveprices/tests/test_templatetags.py
eveprices/tests/utils.py
eveprices/tests/providers/__init__.py
eveprices/tests/providers/evetycoon.py
eveprices/tests/providers/fuzzwork.py
eveprices/tests/providers/janice.py
eveprices/tests/providers/priceinformation.py
aa_eveprices-0.1.3.dist-info/licenses/LICENSE
aa_eveprices-0.1.3.dist-info/WHEEL
aa_eveprices-0.1.3.dist-info/METADATA
aa_eveprices-0.1.3.dist-info/RECORD
